pymunge/__init__.py
swbf_pymunge-0.0.1.dist-info/LICENSE
swbf_pymunge-0.0.1.dist-info/METADATA
swbf_pymunge-0.0.1.dist-info/WHEEL
swbf_pymunge-0.0.1.dist-info/top_level.txt
swbf_pymunge-0.0.1.dist-info/RECORD
