Metadata-Version: 2.2
Name: swbf-pymunge
Version: 0.0.1
Summary: SWBF Python munger
Author: styinx
License: MIT License
Project-URL: Homepage, https://github.com/styinx/pymunge
Project-URL: Issues, https://github.com/styinx/pymunge/issues
Classifier: Development Status :: 3 - Alpha
Classifier: Intended Audience :: Developers
Classifier: Operating System :: OS Independent
Classifier: Programming Language :: Python :: 3.11
Classifier: Topic :: Text Processing
Classifier: Topic :: Utilities
Requires-Python: >=3.11
License-File: LICENSE
